solus/__init__.py
solus/core.py
solus/py.typed
solus-1.2.1.dist-info/LICENSE
solus-1.2.1.dist-info/METADATA
solus-1.2.1.dist-info/WHEEL
solus-1.2.1.dist-info/RECORD
