Metadata-Version: 2.1
Name: solus
Version: 1.2.1
Summary: Singleton types.
Home-page: https://github.com/nekitdev/solus
License: MIT
Keywords: python,singleton
Author: nekitdev
Requires-Python: >=3.8
Classifier: Development Status :: 5 - Production/Stable
Classifier: Intended Audience :: Developers
Classifier: License :: OSI Approved :: MIT License
Classifier: Operating System :: OS Independent
Classifier: Programming Language :: Python :: 3
Classifier: Programming Language :: Python :: 3.8
Classifier: Programming Language :: Python :: 3.9
Classifier: Programming Language :: Python :: 3.10
Classifier: Programming Language :: Python :: 3.11
Classifier: Programming Language :: Python :: 3.12
Classifier: Topic :: Utilities
Classifier: Typing :: Typed
Requires-Dist: named (>=1.4.0,<2.0.0)
Project-URL: Chat, https://nekit.dev/chat
Project-URL: Documentation, https://nekitdev.github.io/solus
Project-URL: Funding, https://nekit.dev/funding
Project-URL: Issues, https://github.com/nekitdev/solus/issues
Project-URL: Repository, https://github.com/nekitdev/solus
